.hgignore
CHANGES.txt
LICENSE.txt
README.txt
bootstrap.py
buildout.cfg
hgtools-1.0b3-py2.6.egg
setup.py
js/__init__.py
js.jsgettext.egg-info/PKG-INFO
js.jsgettext.egg-info/SOURCES.txt
js.jsgettext.egg-info/dependency_links.txt
js.jsgettext.egg-info/entry_points.txt
js.jsgettext.egg-info/namespace_packages.txt
js.jsgettext.egg-info/not-zip-safe
js.jsgettext.egg-info/requires.txt
js.jsgettext.egg-info/top_level.txt
js/jsgettext/__init__.py
js/jsgettext/test_jsgettext.txt
js/jsgettext/resources/Gettext.js
js/jsgettext/resources/README.txt