Metadata-Version: 1.0
Name: js.jsgettext
Version: 0.08
Summary: Fanstatic packaging of jsgettext
Home-page: UNKNOWN
Author: Fanstatic Developers
Author-email: fanstatic@googlegroups.com
License: BSD
Platform: UNKNOWN
